tcp/__init__.py
tcp/_version.py
tcp/client.py
tcp/clientAPI.py
tcp/exceptions.py
tcp/logs.py
tcp/text_serializer.py
tcp/track_usage.py
tcp/upload.py
tcp_sdk-1.0.29.dist-info/METADATA
tcp_sdk-1.0.29.dist-info/WHEEL
tcp_sdk-1.0.29.dist-info/licenses/LICENSE.txt
tcp_sdk-1.0.29.dist-info/RECORD
